discord_logging_handler/__init__.py
discord_logging_handler/handler.py
discord_logging_handler-0.2.0.dist-info/METADATA
discord_logging_handler-0.2.0.dist-info/WHEEL
discord_logging_handler-0.2.0.dist-info/top_level.txt
discord_logging_handler-0.2.0.dist-info/RECORD
