Metadata-Version: 2.4
Name: discord-logging-handler
Version: 0.2.0
Summary: A logging handler that sends log messages to discord via webhook.
Author: Moses White
Classifier: Programming Language :: Python :: 3
Classifier: License :: OSI Approved :: MIT License
Requires-Python: >=3.12
Requires-Dist: requests>=2.28
Dynamic: author
Dynamic: classifier
Dynamic: description
Dynamic: description-content-type
Dynamic: requires-dist
Dynamic: requires-python
Dynamic: summary
